{
  "total_interactions": 6,
  "speakers": {
    "Person 1": {
      "interaction_count": 4,
      "cluster_id": "-1",
      "is_identified": false,
      "name": null
    },
    "Person 2": {
      "interaction_count": 2,
      "cluster_id": "-1",
      "is_identified": false,
      "name": null
    }
  },
  "sample_interactions": [
    {
      "text": "I'll schedule that meeting. Should I include the budget presentation slides?",
      "speaker": "Person 2",
      "entities": [],
      "sentiment": 0.5,
      "timestamp": "2024-01-15 09:01:45"
    },
    {
      "text": "Yes, please include the slides. The meeting room should be Conference Room A.",
      "speaker": "Person 1",
      "entities": [],
      "sentiment": 0.5,
      "timestamp": "2024-01-15 09:02:15"
    },
    {
      "text": "Hey, I'm back from lunch. Can you text my mom that I'll be late tonight?",
      "speaker": "Person 1",
      "entities": [
        {
          "text": "late tonight",
          "label": "TIME",
          "start": 59,
          "end": 71
        }
      ],
      "sentiment": 0.5,
      "timestamp": "2024-01-15 10:30:00"
    }
  ],
  "configuration": {
    "short_term_window": 10,
    "max_history_size": 1000,
    "max_conversation_length": 5,
    "conversation_gap_threshold": 300,
    "similarity_threshold": 0.75,
    "max_speakers": 10,
    "dbscan_eps": 0.3,
    "dbscan_min_samples": 2,
    "voice_embedding_update_rate": 0.1,
    "enable_ner": true,
    "enable_coreference": true,
    "enable_topic_modeling": true,
    "enable_sentiment_analysis": true,
    "spacy_model": "en_core_web_sm",
    "max_topics": 5,
    "long_term_context_max_results": 5,
    "context_similarity_threshold": 0.7,
    "enable_context_summarization": true,
    "summary_max_length": 200,
    "batch_processing": false,
    "cache_embeddings": true,
    "async_processing": false,
    "debug_mode": false,
    "log_level": "INFO",
    "save_intermediate_results": false
  }
}